aria_mps_cli/__init__.py
aria_mps_cli/cli.py
aria_mps_cli/cli_lib/__init__.py
aria_mps_cli/cli_lib/authentication.py
aria_mps_cli/cli_lib/base_state_machine.py
aria_mps_cli/cli_lib/common.py
aria_mps_cli/cli_lib/config_updatable.py
aria_mps_cli/cli_lib/constants.py
aria_mps_cli/cli_lib/device_version_check.py
aria_mps_cli/cli_lib/downloader.py
aria_mps_cli/cli_lib/eligibility_check.py
aria_mps_cli/cli_lib/encryption.py
aria_mps_cli/cli_lib/error_screen.py
aria_mps_cli/cli_lib/hash_calculator.py
aria_mps_cli/cli_lib/health_check.py
aria_mps_cli/cli_lib/http_helper.py
aria_mps_cli/cli_lib/login_screen.py
aria_mps_cli/cli_lib/mma_screen.py
aria_mps_cli/cli_lib/mps.py
aria_mps_cli/cli_lib/mps_app.py
aria_mps_cli/cli_lib/multi_recording_mps.py
aria_mps_cli/cli_lib/multi_recording_request.py
aria_mps_cli/cli_lib/quit_screen.py
aria_mps_cli/cli_lib/request_monitor.py
aria_mps_cli/cli_lib/response_parser.py
aria_mps_cli/cli_lib/run.py
aria_mps_cli/cli_lib/runner_with_progress.py
aria_mps_cli/cli_lib/single_recording_mps.py
aria_mps_cli/cli_lib/single_recording_request.py
aria_mps_cli/cli_lib/types.py
aria_mps_cli/cli_lib/uploader.py
aria_mps_cli/cli_lib/username_screen.py
projectaria_mps-1.0.1.dist-info/licenses/LICENSE
projectaria_mps-1.0.1.dist-info/METADATA
projectaria_mps-1.0.1.dist-info/WHEEL
projectaria_mps-1.0.1.dist-info/entry_points.txt
projectaria_mps-1.0.1.dist-info/top_level.txt
projectaria_mps-1.0.1.dist-info/RECORD
